pingme/__init__.py
pingme/_modidx.py
pingme/api.py
pingme/core.py
pingme/hello_world.py
pingme/pingme_class.py
pingme/config/config.default.env
pingme/config/config.default.yaml
ssi_pingme_note_name_override_due_to_collision-0.0.4.dist-info/LICENSE
ssi_pingme_note_name_override_due_to_collision-0.0.4.dist-info/METADATA
ssi_pingme_note_name_override_due_to_collision-0.0.4.dist-info/WHEEL
ssi_pingme_note_name_override_due_to_collision-0.0.4.dist-info/entry_points.txt
ssi_pingme_note_name_override_due_to_collision-0.0.4.dist-info/top_level.txt
ssi_pingme_note_name_override_due_to_collision-0.0.4.dist-info/RECORD
