Metadata-Version: 2.2
Name: ssi_pingme-note-name-override-due-to-collision
Version: 0.0.4
Summary: TODO
Home-page: https://github.com/$GIT_USER_NAME/pingme
Author: $GIT_USER_NAME
Author-email: kimleeng@gmail.com
License: MIT License
Keywords: nbdev jupyter notebook python
Classifier: Development Status :: 4 - Beta
Classifier: Intended Audience :: Developers
Classifier: Natural Language :: English
Classifier: Programming Language :: Python :: 3.7
Classifier: Programming Language :: Python :: 3.8
Classifier: Programming Language :: Python :: 3.9
Classifier: Programming Language :: Python :: 3.10
Classifier: License :: OSI Approved :: MIT License
Requires-Python: >=3.7
License-File: LICENSE
Requires-Dist: fastcore
Requires-Dist: setuptools
Requires-Dist: pydantic-settings
Requires-Dist: pydantic
Requires-Dist: python_dotenv
Requires-Dist: envyaml
Requires-Dist: pandas
Requires-Dist: black
Requires-Dist: requests
Requires-Dist: uvicorn
Requires-Dist: fastapi
Requires-Dist: httpx
Provides-Extra: dev
Dynamic: author
Dynamic: author-email
Dynamic: classifier
Dynamic: description
Dynamic: description-content-type
Dynamic: home-page
Dynamic: keywords
Dynamic: license
Dynamic: provides-extra
Dynamic: requires-dist
Dynamic: requires-python
Dynamic: summary
